seas5tools/__init__.py
seas5tools/seas5tools.py
seas5tools/clims/sst_1993_2016.zarr/.zattrs
seas5tools/clims/sst_1993_2016.zarr/.zgroup
seas5tools/clims/sst_1993_2016.zarr/.zmetadata
seas5tools/clims/sst_1993_2016.zarr/fmonth/.zarray
seas5tools/clims/sst_1993_2016.zarr/fmonth/.zattrs
seas5tools/clims/sst_1993_2016.zarr/fmonth/0
seas5tools/clims/sst_1993_2016.zarr/latitude/.zarray
seas5tools/clims/sst_1993_2016.zarr/latitude/.zattrs
seas5tools/clims/sst_1993_2016.zarr/latitude/0
seas5tools/clims/sst_1993_2016.zarr/longitude/.zarray
seas5tools/clims/sst_1993_2016.zarr/longitude/.zattrs
seas5tools/clims/sst_1993_2016.zarr/longitude/0
seas5tools/clims/sst_1993_2016.zarr/mean/.zarray
seas5tools/clims/sst_1993_2016.zarr/mean/.zattrs
seas5tools/clims/sst_1993_2016.zarr/mean/0.0.0.0
seas5tools/clims/sst_1993_2016.zarr/mean/0.0.0.1
seas5tools/clims/sst_1993_2016.zarr/mean/0.0.1.0
seas5tools/clims/sst_1993_2016.zarr/mean/0.0.1.1
seas5tools/clims/sst_1993_2016.zarr/mean/0.1.0.0
seas5tools/clims/sst_1993_2016.zarr/mean/0.1.0.1
seas5tools/clims/sst_1993_2016.zarr/mean/0.1.1.0
seas5tools/clims/sst_1993_2016.zarr/mean/0.1.1.1
seas5tools/clims/sst_1993_2016.zarr/mean/0.2.0.0
seas5tools/clims/sst_1993_2016.zarr/mean/0.2.0.1
seas5tools/clims/sst_1993_2016.zarr/mean/0.2.1.0
seas5tools/clims/sst_1993_2016.zarr/mean/0.2.1.1
seas5tools/clims/sst_1993_2016.zarr/mean/0.3.0.0
seas5tools/clims/sst_1993_2016.zarr/mean/0.3.0.1
seas5tools/clims/sst_1993_2016.zarr/mean/0.3.1.0
seas5tools/clims/sst_1993_2016.zarr/mean/0.3.1.1
seas5tools/clims/sst_1993_2016.zarr/mean/1.0.0.0
seas5tools/clims/sst_1993_2016.zarr/mean/1.0.0.1
seas5tools/clims/sst_1993_2016.zarr/mean/1.0.1.0
seas5tools/clims/sst_1993_2016.zarr/mean/1.0.1.1
seas5tools/clims/sst_1993_2016.zarr/mean/1.1.0.0
seas5tools/clims/sst_1993_2016.zarr/mean/1.1.0.1
seas5tools/clims/sst_1993_2016.zarr/mean/1.1.1.0
seas5tools/clims/sst_1993_2016.zarr/mean/1.1.1.1
seas5tools/clims/sst_1993_2016.zarr/mean/1.2.0.0
seas5tools-0.0.9.dist-info/METADATA
seas5tools-0.0.9.dist-info/WHEEL
seas5tools-0.0.9.dist-info/licenses/LICENSE
seas5tools-0.0.9.dist-info/RECORD
